edalite/__init__.py
edalite/depreciate/core copy.py
edalite/depreciate/core2.py
edalite/pubsub.py
edalite/queue.py
edalite-0.6.0.dist-info/METADATA
edalite-0.6.0.dist-info/WHEEL
edalite-0.6.0.dist-info/RECORD
